data/__init__.py
data/datasets.py
data/urls.py
xiu/__init__.py
xiu/datasets.py
xiu/urls.py
xiu-0.0.6.dist-info/METADATA
xiu-0.0.6.dist-info/WHEEL
xiu-0.0.6.dist-info/entry_points.txt
xiu-0.0.6.dist-info/top_level.txt
xiu-0.0.6.dist-info/RECORD
