Metadata-Version: 2.1
Name: xiu
Version: 0.0.6
Summary: XIUXIU
Home-page: https://github.com/private_repo/codefast
Author: R2FsCg
Author-email: r2fscg@gmail.com
License: UNKNOWN
Platform: UNKNOWN
Classifier: Programming Language :: Python :: 3
Classifier: License :: OSI Approved :: MIT License
Classifier: Operating System :: OS Independent
Requires-Dist: codefast
